cyclicityanalysis/__init__.py
cyclicityanalysis/coom.py
cyclicityanalysis/orientedarea.py
cyclicityanalysis-1.0.5.dist-info/LICENSE
cyclicityanalysis-1.0.5.dist-info/METADATA
cyclicityanalysis-1.0.5.dist-info/WHEEL
cyclicityanalysis-1.0.5.dist-info/top_level.txt
cyclicityanalysis-1.0.5.dist-info/RECORD
