Metadata-Version: 2.1
Name: cyclicityanalysis
Version: 1.0.5
Summary: Performs Cyclicity Analysis on A Collection of Time-Series
Author-email: Vivek Kaushik <vskaush2@illinois.edu>
License: MIT
Classifier: Programming Language :: Python :: 3
Requires-Python: >=3.10
License-File: LICENSE
Requires-Dist: numpy
Requires-Dist: pandas
Provides-Extra: optional_dependencies
Requires-Dist: pytest ; extra == 'optional_dependencies'
Requires-Dist: jupyter ; extra == 'optional_dependencies'
Requires-Dist: requests ; extra == 'optional_dependencies'
Requires-Dist: scipy ; extra == 'optional_dependencies'
Requires-Dist: matplotlib ; extra == 'optional_dependencies'
Requires-Dist: seaborn ; extra == 'optional_dependencies'
